kozai/__init__.py
kozai/_kozai_constants.py
kozai/delaunay.py
kozai/ekm.py
kozai/kl_period.py
kozai/vectorial.py
kozai-0.3.0.data/scripts/kozai
kozai-0.3.0.data/scripts/kozai-ekm
kozai-0.3.0.data/scripts/kozai-test-particle
kozai-0.3.0.dist-info/LICENSE
kozai-0.3.0.dist-info/METADATA
kozai-0.3.0.dist-info/WHEEL
kozai-0.3.0.dist-info/top_level.txt
kozai-0.3.0.dist-info/RECORD
