Metadata-Version: 2.1
Name: kozai
Version: 0.3.0
Summary: Evolve hierarchical triples.
Home-page: https://github.com/joe-antognini/kozai
Author: Joseph O'Brien Antognini
Author-email: joe.antognini@gmail.com
License: MIT
Keywords: kozai lidov triple dynamics orbit star
Platform: UNKNOWN
Classifier: Development Status :: 4 - Beta
Classifier: Intended Audience :: Science/Research
Classifier: License :: OSI Approved :: MIT License
Classifier: Programming Language :: Python :: 2.7
Classifier: Topic :: Scientific/Engineering :: Astronomy
Classifier: Topic :: Scientific/Engineering :: Physics
Requires-Python: >=3.6
Requires-Dist: numpy (>=1.18.4)
Requires-Dist: scipy (>=1.4.1)
